Changelog
MANIFEST.in
README
setup.py
cms_pictures_polaroid/__init__.py
cms_pictures_polaroid/cms_plugins.py
cms_pictures_polaroid/models.py
cms_pictures_polaroid/static/cms_pictures_polaroid/css/.jquery_rotate_plugin.css.swp
cms_pictures_polaroid/static/cms_pictures_polaroid/css/jquery_rotate_plugin.css
cms_pictures_polaroid/static/cms_pictures_polaroid/images/polaroid.png
cms_pictures_polaroid/static/cms_pictures_polaroid/js/jquery.js
cms_pictures_polaroid/static/cms_pictures_polaroid/js/jquery.rotate.js
cms_pictures_polaroid/static/cms_pictures_polaroid/js/jquery.rotate.min.js
cms_pictures_polaroid/templates/cms_pictures_polaroid/polaroid.html
cms_pictures_slider/__init__.py
cms_pictures_slider/admin.py
cms_pictures_slider/cms_plugins.py
cms_pictures_slider/models.py
cms_pictures_slider/static/cms_pictures_slider/css/default.css
cms_pictures_slider/static/cms_pictures_slider/css/nivo-slider.css
cms_pictures_slider/static/cms_pictures_slider/css/style.css
cms_pictures_slider/static/cms_pictures_slider/img/arrows.png
cms_pictures_slider/static/cms_pictures_slider/img/bullets.png
cms_pictures_slider/static/cms_pictures_slider/img/loading.gif
cms_pictures_slider/static/cms_pictures_slider/js/jquery-1.6.1.min.js
cms_pictures_slider/static/cms_pictures_slider/js/jquery.nivo.slider.pack.js
cms_pictures_slider/templates/cms_pictures_slider/slider.html
django_cms_pictures.egg-info/PKG-INFO
django_cms_pictures.egg-info/SOURCES.txt
django_cms_pictures.egg-info/dependency_links.txt
django_cms_pictures.egg-info/not-zip-safe
django_cms_pictures.egg-info/requires.txt
django_cms_pictures.egg-info/top_level.txt