Metadata-Version: 1.0
Name: django-cms-pictures
Version: 0.0.1
Summary: Django CMS Pictures Plugins
Home-page: http://github.com/psaavedra/django-cms-pictures
Author: Pablo Saavedra
Author-email: pablo.saavedra@treitos.com
License: Copyright (R) 2011 Treitos
